Metadata-Version: 2.1
Name: dktoloaddotenv
Version: 1.0.0a0
Summary: Load .env (dotenv) files
Home-page: https://discord-catho.frama.io/load_dotenv
Author: Pierre
License: UNKNOWN
Project-URL: Source Code, https://framagit.org/discord-catho/load_dotenv
Keywords: dotenv,.env
Platform: UNKNOWN
Requires-Python: <4,>=3.9
Provides-Extra: doc
Provides-Extra: tests
